yato/__init__.py
yato/main.py
yato/yato.py
yato/model/__init__.py
yato/model/charbigru.py
yato/model/charbilstm.py
yato/model/charcnn.py
yato/model/classificationhead.py
yato/model/crf.py
yato/model/customModel.py
yato/model/ncrf_transformers.py
yato/model/sentclassifier.py
yato/model/seqlabel.py
yato/model/wordrep.py
yato/model/wordsequence.py
yato/utils/__init__.py
yato/utils/alphabet.py
yato/utils/data.py
yato/utils/functions.py
yato/utils/metric.py
yato/utils/tagSchemeConverter.py
yato/utils/text_attention.py
ylab_yato-0.1.2.dist-info/LICENSE
ylab_yato-0.1.2.dist-info/METADATA
ylab_yato-0.1.2.dist-info/WHEEL
ylab_yato-0.1.2.dist-info/top_level.txt
ylab_yato-0.1.2.dist-info/RECORD
