Metadata-Version: 2.1
Name: ylab-yato
Version: 0.1.2
Summary: YATO: Yet Another deep learning based Text analysis Open toolkit
Home-page: https://github.com/jiesutd/YATO
Author: Jie Yang, Zeqiang Wang
Author-email: y@zju.edu.cn
License: Apache License II
Classifier: License :: OSI Approved :: MIT License
Classifier: Programming Language :: Python
Classifier: Programming Language :: Python :: 3
Classifier: Programming Language :: Python :: 3.6
Classifier: Programming Language :: Python :: Implementation :: CPython
Classifier: Programming Language :: Python :: Implementation :: PyPy
Requires-Python: >=3.6.0
License-File: LICENSE
Requires-Dist: torch (>1.1.0)
Requires-Dist: transformers (>=4.10.2)
